currency_quote/__init__.py
currency_quote/__main.py
currency_quote/adapters/inbound/lib_controller.py
currency_quote/adapters/outbound/currency_api.py
currency_quote/adapters/outbound/currency_validator_api.py
currency_quote/application/ports/inbound/controller.py
currency_quote/application/ports/outbound/currency_repository.py
currency_quote/application/ports/outbound/currency_validator_repository.py
currency_quote/application/use_cases/get_history_currency_quote.py
currency_quote/application/use_cases/get_last_currency_quote.py
currency_quote/application/use_cases/validate_currency.py
currency_quote/config/endpoints.py
currency_quote/domain/entities/currency.py
currency_quote/domain/services/get_currency_quote.py
currency_quote/domain/services/validate_currency.py
currency_quote/utils/logger.py
currency_quote-5.0.5.dist-info/LICENSE
currency_quote-5.0.5.dist-info/METADATA
currency_quote-5.0.5.dist-info/WHEEL
currency_quote-5.0.5.dist-info/RECORD
