Metadata-Version: 2.1
Name: currency-quote
Version: 5.0.5
Summary: Complete solution for extracting currency pair quotes data. With comprehensive testing, parameter validation, flexible configuration management, Hexagonal Architecture, CI/CD pipelines, code quality tools, and detailed documentation.
License: MIT
Author: IvanildoBarauna
Author-email: ivanildo.jnr@outlook.com
Requires-Python: >=3.9,<4.0
Classifier: Development Status :: 5 - Production/Stable
Classifier: Intended Audience :: Developers
Classifier: License :: OSI Approved :: MIT License
Classifier: Programming Language :: Python :: 3
Classifier: Programming Language :: Python :: 3.9
Classifier: Programming Language :: Python :: 3.10
Classifier: Programming Language :: Python :: 3.11
Classifier: Programming Language :: Python :: 3.8
Requires-Dist: api-to-dataframe (>=2.0.0,<3.0.0)
Requires-Dist: pytest (>=8.3.4,<9.0.0)
Project-URL: ArchDesign, https://github.com/IvanildoBarauna/currency-quote-wrapper/blob/main/hexagonal_design_arch.png
Project-URL: Homepage, https://pypi.org/project/currency-quote-wrapper
Project-URL: Issues, https://github.com/IvanildoBarauna/currency-quote-wrapper/issues
Project-URL: Repository, https://github.com/IvanildoBarauna/currency-quote-wrapper
Project-URL: README, https://github.com/IvanildoBarauna/currency-quote-wrapper/blob/main/README.md
